MANIFEST.in
README.txt
README_SETUP.txt
aksetup_helper.py
configure.py
setup.cfg
setup.py
c++/defs.cpp
c++/steme_defs_pch.h
c++/steme_python_pch.h
c++/FAST/HS-algorithm.h
c++/FAST/HS-list-shift.cpp
c++/FAST/HS-options.h
c++/FAST/HS.cpp
c++/FAST/HS.h
c++/FAST/basic_pruning.cpp
c++/FAST/basic_pruning.h
c++/FAST/brent.h
c++/FAST/complex.h
c++/FAST/convolution.cpp
c++/FAST/convolution.h
c++/FAST/entropy-combined.cpp
c++/FAST/entropy-combined.h
c++/FAST/entropy-test.cpp
c++/FAST/entropy.cpp
c++/FAST/entropy.h
c++/FAST/extended_exponent.h
c++/FAST/fft.cpp
c++/FAST/fft.h
c++/FAST/fftw3.h
c++/FAST/list.h
c++/FAST/llr_score.cpp
c++/FAST/llr_score.h
c++/FAST/me-test.cpp
c++/FAST/minimize.cpp
c++/FAST/minimize.h
c++/FAST/mnbrak.h
c++/FAST/motif_evaluator.cpp
c++/FAST/motif_evaluator.h
c++/FAST/multi_pmf.h
c++/FAST/multinom_prob.cpp
c++/FAST/multinom_prob.h
c++/FAST/naive_enumeration.cpp
c++/FAST/theta_fns.cpp
c++/FAST/theta_fns.h
c++/FAST/utils.cpp
c++/FAST/utils.h
c++/FAST/wisdom
c++/hmm/hmm/baum_welch.h
c++/hmm/hmm/consensus.h
c++/hmm/hmm/count_mers.h
c++/hmm/hmm/defs.h
c++/hmm/hmm/forward_backward.h
c++/hmm/hmm/markov_order.h
c++/hmm/hmm/model.h
c++/hmm/hmm/model_conversion.h
c++/hmm/hmm/model_state.h
c++/hmm/hmm/parameters.h
c++/hmm/hmm/pssm_model.h
c++/hmm/hmm/python.h
c++/hmm/hmm/sample.h
c++/hmm/hmm/simple_pssm.h
c++/hmm/hmm/training.h
c++/hmm/hmm/viterbi.h
c++/hmm/hmm/viterbi_training.h
c++/hmm/multi-array-speed-test/multi-array-speed-test.cpp
c++/hmm/myrrh/myrrh/application.h
c++/hmm/myrrh/myrrh/assert.h
c++/hmm/myrrh/myrrh/bit_set.h
c++/hmm/myrrh/myrrh/chain_iterator.h
c++/hmm/myrrh/myrrh/defs.h
c++/hmm/myrrh/myrrh/fpu.h
c++/hmm/myrrh/myrrh/math.h
c++/hmm/myrrh/myrrh/seqan_boost_range_adaptors.h
c++/hmm/myrrh/myrrh/serialisable.h
c++/hmm/myrrh/myrrh/store_n_best.h
c++/hmm/myrrh/myrrh/suffix_tree.h
c++/hmm/myrrh/myrrh/suffix_tree_graph.h
c++/hmm/myrrh/myrrh/trie.h
c++/hmm/myrrh/myrrh/type_names.h
c++/hmm/myrrh/myrrh/types.h
c++/hmm/myrrh/myrrh/python/boost_function.h
python/STEME.egg-info/PKG-INFO
python/STEME.egg-info/SOURCES.txt
python/STEME.egg-info/dependency_links.txt
python/STEME.egg-info/not-zip-safe
python/STEME.egg-info/requires.txt
python/STEME.egg-info/top_level.txt
